{
	"success": true,
	"status": 0,
	"message": "success",
	"code": 200,
	"data": {
		"id": 7,
		"androidVersion": "",
		"androidMinVersion": "",
		"iosVersion": "",
		"iosMinVersion": "",
		"onlineName": "Operation Function",
		"userSettings": true,
		"contentList": [{
			"name": "Homepage Functions",
			"list": [{
				"id": 378,
				"title": "Futures",
				"introduction": "",
				"imgUrl": "https://huobi-1253283450.file.myqcloud.com/bit/appFeatures/07326dfc-91e6-43a5-a91f-01da727479d3.png",
				"imgNightUrl": "https://huobi-1253283450.file.myqcloud.com/bit/appFeatures/9cc9bb0b-49f8-4350-9490-2b8764cb6ae6.png",
				"subUrl": "",
				"jumpMode": 31,
				"jumpUrl": "",
				"jumpSymbol": "",
				"weight": 110,
				"needLogin": 0,
				"androidVersion": "",
				"androidMinVersion": "",
				"iosVersion": "",
				"iosMinVersion": "",
				"description": "",
				"group": "Trade",
				"startTime": 0,
				"endTime": 0,
				"androidMaxVersion": "",
				"iosMaxVersion": "",
				"domainUrlBusiness": "",
				"countryBlackList": "",
				"newImgUrl": "https://huobi-1306115679.file.myqcloud.com/bit/appFeatures/17b22186-fcb1-4c79-b41f-d51ff809aa58.png",
				"groupCode": "USDT合约",
				"homePageFixed": 1,
				"homePageFixedIndex": 110,
				"newModule": null,
				"sort": null
			}, {
				"id": 379,
				"title": "Trading Bot",
				"introduction": "",
				"imgUrl": "https://huobi-1253283450.file.myqcloud.com/bit/appFeatures/dd57221d-f9af-4116-a141-3f1ba2315a28.png",
				"imgNightUrl": "https://huobi-1253283450.file.myqcloud.com/bit/appFeatures/f840e92c-dcc6-4810-be79-f4ac295f8e7b.png",
				"subUrl": "",
				"jumpMode": 1,
				"jumpUrl": "https://www.huobi.co.ma/en-us/tradingbot/h5",
				"jumpSymbol": "",
				"weight": 109,
				"needLogin": 0,
				"androidVersion": "",
				"androidMinVersion": "",
				"iosVersion": "",
				"iosMinVersion": "",
				"description": "",
				"group": "Trade",
				"startTime": 0,
				"endTime": 0,
				"androidMaxVersion": "",
				"iosMaxVersion": "",
				"domainUrlBusiness": "主站域名",
				"countryBlackList": "",
				"newImgUrl": "https://huobi-1306115679.file.myqcloud.com/bit/appFeatures/66ce8caf-a8ce-4301-a11e-8e75a60464b8.png",
				"groupCode": "网格机器人",
				"homePageFixed": 1,
				"homePageFixedIndex": 109,
				"newModule": null,
				"sort": null
			}, {
				"id": 1014,
				"title": "Huobi NFT",
				"introduction": "",
				"imgUrl": "https://huobi-1253283450.file.myqcloud.com/bit/appFeatures/8d43564f-9814-4460-8c60-99da9c14bc7d.png",
				"imgNightUrl": "https://huobi-1253283450.file.myqcloud.com/bit/appFeatures/d87989b0-7843-4a37-8e78-6cf3915eb324.png",
				"subUrl": "",
				"jumpMode": 1,
				"jumpUrl": "https://nft.huobi.co.ma/en-us",
				"jumpSymbol": "",
				"weight": 108,
				"needLogin": 0,
				"androidVersion": "",
				"androidMinVersion": "",
				"iosVersion": "",
				"iosMinVersion": "",
				"description": "",
				"group": "Trade",
				"startTime": 0,
				"endTime": 0,
				"androidMaxVersion": "",
				"iosMaxVersion": "",
				"domainUrlBusiness": "火币NFT",
				"countryBlackList": "",
				"newImgUrl": "https://huobi-1306115679.file.myqcloud.com/bit/appFeatures/bd6c3a49-4a23-46aa-a79f-625debea5d2a.png",
				"groupCode": "火币NFT",
				"homePageFixed": 1,
				"homePageFixedIndex": 108,
				"newModule": null,
				"sort": null
			}, {
				"id": 1351,
				"title": "Dual Investment",
				"introduction": "",
				"imgUrl": "https://huobi-1306115679.file.myqcloud.com/bit/appFeatures/b295bb58-6456-4ba0-8485-74050bdb863f.png",
				"imgNightUrl": "https://huobi-1306115679.file.myqcloud.com/bit/appFeatures/116604cc-3fa4-47f6-b0e7-16c9227534e8.png",
				"subUrl": "",
				"jumpMode": 1,
				"jumpUrl": "https://www.huobi.co.ma/en-us/otc-option/win/h5",
				"jumpSymbol": "",
				"weight": 107,
				"needLogin": 0,
				"androidVersion": "",
				"androidMinVersion": "",
				"iosVersion": "",
				"iosMinVersion": "",
				"description": "",
				"group": "Finance",
				"startTime": 0,
				"endTime": 0,
				"androidMaxVersion": "",
				"iosMaxVersion": "",
				"domainUrlBusiness": "主站域名",
				"countryBlackList": "",
				"newImgUrl": "https://huobi-1306115679.file.myqcloud.com/bit/appFeatures/7c41a570-8aa9-4e73-a5f3-8878efe53514.png",
				"groupCode": "双币投资",
				"homePageFixed": 1,
				"homePageFixedIndex": 107,
				"newModule": null,
				"sort": null
			}, {
				"id": 376,
				"title": "Deposit",
				"introduction": "",
				"imgUrl": "https://huobi-1253283450.file.myqcloud.com/bit/appFeatures/3b3e121c-1137-45da-a9e3-c103155f34df.png",
				"imgNightUrl": "https://huobi-1253283450.file.myqcloud.com/bit/appFeatures/9e9885f2-0dd2-4679-93b5-c526311fb911.png",
				"subUrl": "",
				"jumpMode": 8,
				"jumpUrl": "",
				"jumpSymbol": "",
				"weight": 106,
				"needLogin": 1,
				"androidVersion": "",
				"androidMinVersion": "",
				"iosVersion": "",
				"iosMinVersion": "",
				"description": "",
				"group": "Trade",
				"startTime": 0,
				"endTime": 0,
				"androidMaxVersion": "",
				"iosMaxVersion": "",
				"domainUrlBusiness": "",
				"countryBlackList": "",
				"newImgUrl": "https://huobi-1306115679.file.myqcloud.com/bit/appFeatures/71db2a18-ed6a-4cd4-b96c-6b9e9a1774d6.png",
				"groupCode": "充币",
				"homePageFixed": 1,
				"homePageFixedIndex": 106,
				"newModule": null,
				"sort": null
			}, {
				"id": 381,
				"title": "Earn",
				"introduction": "",
				"imgUrl": "https://huobi-1253283450.file.myqcloud.com/bit/appFeatures/06fee7d0-c0b5-41ea-91da-8713481655e9.png",
				"imgNightUrl": "https://huobi-1253283450.file.myqcloud.com/bit/appFeatures/aa3ee4c6-fb41-4968-b813-d2612f25160f.png",
				"subUrl": "",
				"jumpMode": 1,
				"jumpUrl": "https://www.huobi.co.ma/en-us/financial/earnings/h5",
				"jumpSymbol": "",
				"weight": 97,
				"needLogin": 1,
				"androidVersion": "",
				"androidMinVersion": "",
				"iosVersion": "",
				"iosMinVersion": "",
				"description": "",
				"group": "Finance",
				"startTime": 0,
				"endTime": 0,
				"androidMaxVersion": "",
				"iosMaxVersion": "",
				"domainUrlBusiness": "主站域名",
				"countryBlackList": "",
				"newImgUrl": "https://huobi-1306115679.file.myqcloud.com/bit/appFeatures/72fb9eac-1740-4938-933f-dee9d04bda37.png",
				"groupCode": "Huobi Earn",
				"homePageFixed": 0,
				"homePageFixedIndex": 0,
				"newModule": null,
				"sort": 26380
			}, {
				"id": 1336,
				"title": "Options",
				"introduction": "",
				"imgUrl": "https://huobi-1306115679.file.myqcloud.com/bit/appFeatures/d3fdb76d-0a7d-435f-bb6e-0eaad98ccc5a.png",
				"imgNightUrl": "https://huobi-1306115679.file.myqcloud.com/bit/appFeatures/3737a54d-1413-4550-9640-fc2cd5314e24.png",
				"subUrl": "",
				"jumpMode": 35,
				"jumpUrl": "",
				"jumpSymbol": "",
				"weight": 95,
				"needLogin": 1,
				"androidVersion": "",
				"androidMinVersion": "",
				"iosVersion": "",
				"iosMinVersion": "",
				"description": "",
				"group": "Trade",
				"startTime": 0,
				"endTime": 0,
				"androidMaxVersion": "",
				"iosMaxVersion": "",
				"domainUrlBusiness": "",
				"countryBlackList": "",
				"newImgUrl": "https://huobi-1306115679.file.myqcloud.com/bit/appFeatures/fc66f78c-0b29-43ee-be43-744aa6b4d275.png",
				"groupCode": "期权",
				"homePageFixed": 0,
				"homePageFixedIndex": 0,
				"newModule": null,
				"sort": 26381
			}, {
				"id": 1523,
				"title": "Margin",
				"introduction": "",
				"imgUrl": "https://huobi-1306115679.file.myqcloud.com/bit/appFeatures/721e39eb-bca0-4fa0-935a-90a3328e3eb1.png",
				"imgNightUrl": "https://huobi-1306115679.file.myqcloud.com/bit/appFeatures/d255ea72-7b72-4315-9bbf-1a3e056b9b35.png",
				"subUrl": "",
				"jumpMode": 20,
				"jumpUrl": "",
				"jumpSymbol": "",
				"weight": 93,
				"needLogin": 1,
				"androidVersion": "",
				"androidMinVersion": "",
				"iosVersion": "",
				"iosMinVersion": "",
				"description": "",
				"group": "Trade",
				"startTime": 0,
				"endTime": 0,
				"androidMaxVersion": "",
				"iosMaxVersion": "",
				"domainUrlBusiness": "",
				"countryBlackList": "",
				"newImgUrl": "https://huobi-1306115679.file.myqcloud.com/bit/appFeatures/024f3d7b-511c-4a17-a4d6-eb06c4042e68.png",
				"groupCode": "杠杆",
				"homePageFixed": 0,
				"homePageFixedIndex": 0,
				"newModule": null,
				"sort": 26382
			}, {
				"id": 1444,
				"title": "Trade Spin",
				"introduction": "",
				"imgUrl": "https://huobi-1306115679.file.myqcloud.com/bit/appFeatures/c86d4cdc-4f6f-4de3-bbb2-ea98d4cd92f5.png",
				"imgNightUrl": "https://huobi-1306115679.file.myqcloud.com/bit/appFeatures/0b203bbe-27dd-4116-a4de-33e4cb581cf7.png",
				"subUrl": "",
				"jumpMode": 1,
				"jumpUrl": "https://www.huobi.co.ma/en-us/topic/trading-activity-tmpl/h5/?code=Lottery220512124654",
				"jumpSymbol": "",
				"weight": 92,
				"needLogin": 1,
				"androidVersion": "6.5.9|6.5.8|6.5.7|6.5.4|",
				"androidMinVersion": "",
				"iosVersion": "6.5.9|6.5.8|6.5.7|6.5.3|6.5.2|",
				"iosMinVersion": "",
				"description": "",
				"group": "Activities and Bonus",
				"startTime": 0,
				"endTime": 0,
				"androidMaxVersion": "",
				"iosMaxVersion": "",
				"domainUrlBusiness": "主站域名",
				"countryBlackList": "",
				"newImgUrl": "https://huobi-1306115679.file.myqcloud.com/bit/appFeatures/dc479aa5-2d67-4b3c-8064-2255eb2b23ac.png",
				"groupCode": "引力",
				"homePageFixed": 0,
				"homePageFixedIndex": 0,
				"newModule": null,
				"sort": 26383
			}, {
				"id": 377,
				"title": "Chat",
				"introduction": "",
				"imgUrl": "https://huobi-1253283450.file.myqcloud.com/bit/appFeatures/cf934879-fad2-41e9-86f0-c5a2fc54090a.png",
				"imgNightUrl": "https://huobi-1253283450.file.myqcloud.com/bit/appFeatures/37a770ce-b00c-4675-99bf-1738415b04d9.png",
				"subUrl": "",
				"jumpMode": 7,
				"jumpUrl": "",
				"jumpSymbol": "",
				"weight": 91,
				"needLogin": 0,
				"androidVersion": "",
				"androidMinVersion": "",
				"iosVersion": "",
				"iosMinVersion": "",
				"description": "",
				"group": "Service",
				"startTime": 0,
				"endTime": 0,
				"androidMaxVersion": "",
				"iosMaxVersion": "",
				"domainUrlBusiness": "",
				"countryBlackList": "",
				"newImgUrl": "https://huobi-1306115679.file.myqcloud.com/bit/appFeatures/8e48e298-7460-4b1d-abcf-088fee084083.png",
				"groupCode": "客服",
				"homePageFixed": 0,
				"homePageFixedIndex": 0,
				"newModule": null,
				"sort": 26384
			}, {
				"id": 1013,
				"title": "Huobi Learn",
				"introduction": "",
				"imgUrl": "https://huobi-1253283450.file.myqcloud.com/bit/appFeatures/719840a4-91ca-4b49-b171-094319ef5886.png",
				"imgNightUrl": "https://huobi-1253283450.file.myqcloud.com/bit/appFeatures/de39037d-44e0-4586-b43a-a84e98377998.png",
				"subUrl": "",
				"jumpMode": 1,
				"jumpUrl": "https://www.huobi.co.ma/learn/en-us/",
				"jumpSymbol": "",
				"weight": 90,
				"needLogin": 0,
				"androidVersion": "",
				"androidMinVersion": "",
				"iosVersion": "",
				"iosMinVersion": "",
				"description": "",
				"group": "Information",
				"startTime": 0,
				"endTime": 0,
				"androidMaxVersion": "",
				"iosMaxVersion": "",
				"domainUrlBusiness": "主站域名",
				"countryBlackList": "",
				"newImgUrl": "https://huobi-1306115679.file.myqcloud.com/bit/appFeatures/c128e6db-b24a-4921-8eec-32d512013100.png",
				"groupCode": "成长学院",
				"homePageFixed": 0,
				"homePageFixedIndex": 0,
				"newModule": null,
				"sort": 26385
			}, {
				"id": 382,
				"title": "ETH 2.0",
				"introduction": "",
				"imgUrl": "https://huobi-1253283450.file.myqcloud.com/bit/appFeatures/3585291e-9f34-4380-b3d9-59be766de553.png",
				"imgNightUrl": "https://huobi-1253283450.file.myqcloud.com/bit/appFeatures/efe7652e-d37a-43d9-af64-22e67c0b83da.png",
				"subUrl": "",
				"jumpMode": 1,
				"jumpUrl": "https://pool.huobi.co.ma/pool/en-us/topic/eth/h5?refresh=2&color=060C30&hideNav=1",
				"jumpSymbol": "",
				"weight": 88,
				"needLogin": 0,
				"androidVersion": "",
				"androidMinVersion": "",
				"iosVersion": "",
				"iosMinVersion": "",
				"description": "",
				"group": "Finance",
				"startTime": 0,
				"endTime": 0,
				"androidMaxVersion": "",
				"iosMaxVersion": "",
				"domainUrlBusiness": "",
				"countryBlackList": "",
				"newImgUrl": "https://huobi-1306115679.file.myqcloud.com/bit/appFeatures/50b5bea9-4c8b-472c-9c27-787574afdb0b.png",
				"groupCode": "以太坊2.0",
				"homePageFixed": 0,
				"homePageFixedIndex": 0,
				"newModule": null,
				"sort": 26386
			}, {
				"id": 682,
				"title": "Crypto Loans",
				"introduction": "",
				"imgUrl": "https://huobi-1253283450.file.myqcloud.com/bit/appFeatures/f5642537-a7b5-47c9-9036-e18fa293d44f.png",
				"imgNightUrl": "https://huobi-1253283450.file.myqcloud.com/bit/appFeatures/9bba46a7-3ffc-4cf2-af95-435885c47c27.png",
				"subUrl": "",
				"jumpMode": 1,
				"jumpUrl": "https://pledge.huobi.co.ma/pledge/?hideNav=1",
				"jumpSymbol": "",
				"weight": 87,
				"needLogin": 1,
				"androidVersion": "6.4.4|6.4.3|6.4.2|6.4.1|6.4.0|6.3.9|6.3.8|",
				"androidMinVersion": "",
				"iosVersion": "6.4.4|6.4.3|6.4.2|6.4.1|6.4.0|6.3.9|6.3.8|",
				"iosMinVersion": "",
				"description": "",
				"group": "Finance",
				"startTime": 0,
				"endTime": 0,
				"androidMaxVersion": "",
				"iosMaxVersion": "",
				"domainUrlBusiness": "质押借贷",
				"countryBlackList": "",
				"newImgUrl": "https://huobi-1306115679.file.myqcloud.com/bit/appFeatures/f11e8780-6e60-4022-b823-0bd48474afa4.png",
				"groupCode": "质押借币",
				"homePageFixed": 0,
				"homePageFixedIndex": 0,
				"newModule": null,
				"sort": 26387
			}, {
				"id": 475,
				"title": "Staking",
				"introduction": "",
				"imgUrl": "https://huobi-1253283450.file.myqcloud.com/bit/appFeatures/4ebc1f9e-8317-4f63-98a8-e3772ee092c2.png",
				"imgNightUrl": "https://huobi-1253283450.file.myqcloud.com/bit/appFeatures/1cc6d0ba-93da-445a-b801-7b038a0733d5.png",
				"subUrl": "",
				"jumpMode": 1,
				"jumpUrl": "https://www.huobi.co.ma/en-us/staking/vote/h5",
				"jumpSymbol": "",
				"weight": 86,
				"needLogin": 0,
				"androidVersion": "6.3.2|6.3.1|",
				"androidMinVersion": "",
				"iosVersion": "6.3.2|6.3.1|",
				"iosMinVersion": "",
				"description": "",
				"group": "Finance",
				"startTime": 0,
				"endTime": 0,
				"androidMaxVersion": "",
				"iosMaxVersion": "",
				"domainUrlBusiness": "主站域名",
				"countryBlackList": "",
				"newImgUrl": "https://huobi-1306115679.file.myqcloud.com/bit/appFeatures/848df22c-4fb2-45e0-85d8-9c73446ae58c.png",
				"groupCode": "节点投票",
				"homePageFixed": 0,
				"homePageFixedIndex": 0,
				"newModule": null,
				"sort": 26388
			}, {
				"id": 1213,
				"title": "Derivatives Grid Bot",
				"introduction": "",
				"imgUrl": "https://huobi-1253283450.file.myqcloud.com/bit/appFeatures/df7d0943-fd7d-41f3-adab-ae7bcab3ec48.png",
				"imgNightUrl": "https://huobi-1253283450.file.myqcloud.com/bit/appFeatures/13e80d22-6de6-4d1f-94a7-e8a7de385450.png",
				"subUrl": "",
				"jumpMode": 1,
				"jumpUrl": "https://hdm.huobi.co.ma/strategy/grid_exchange/",
				"jumpSymbol": "",
				"weight": 60,
				"needLogin": 1,
				"androidVersion": "",
				"androidMinVersion": "",
				"iosVersion": "",
				"iosMinVersion": "",
				"description": "",
				"group": "Trade",
				"startTime": 0,
				"endTime": 0,
				"androidMaxVersion": "",
				"iosMaxVersion": "",
				"domainUrlBusiness": "合约域名",
				"countryBlackList": "",
				"newImgUrl": "https://huobi-1306115679.file.myqcloud.com/bit/appFeatures/5475f1bb-dcb7-4fbd-803a-465501246142.png",
				"groupCode": "合约网格",
				"homePageFixed": 0,
				"homePageFixedIndex": 0,
				"newModule": null,
				"sort": 26389
			}]
		}, {
			"name": "Trade",
			"list": [{
				"id": 378,
				"title": "Futures",
				"introduction": "",
				"imgUrl": "https://huobi-1253283450.file.myqcloud.com/bit/appFeatures/07326dfc-91e6-43a5-a91f-01da727479d3.png",
				"imgNightUrl": "https://huobi-1253283450.file.myqcloud.com/bit/appFeatures/9cc9bb0b-49f8-4350-9490-2b8764cb6ae6.png",
				"subUrl": "",
				"jumpMode": 31,
				"jumpUrl": "",
				"jumpSymbol": "",
				"weight": 110,
				"needLogin": 0,
				"androidVersion": "",
				"androidMinVersion": "",
				"iosVersion": "",
				"iosMinVersion": "",
				"description": "",
				"group": "Trade",
				"startTime": 0,
				"endTime": 0,
				"androidMaxVersion": "",
				"iosMaxVersion": "",
				"domainUrlBusiness": "",
				"countryBlackList": "",
				"newImgUrl": "https://huobi-1306115679.file.myqcloud.com/bit/appFeatures/17b22186-fcb1-4c79-b41f-d51ff809aa58.png",
				"groupCode": "USDT合约",
				"homePageFixed": 1,
				"homePageFixedIndex": 110,
				"newModule": null,
				"sort": null
			}, {
				"id": 379,
				"title": "Trading Bot",
				"introduction": "",
				"imgUrl": "https://huobi-1253283450.file.myqcloud.com/bit/appFeatures/dd57221d-f9af-4116-a141-3f1ba2315a28.png",
				"imgNightUrl": "https://huobi-1253283450.file.myqcloud.com/bit/appFeatures/f840e92c-dcc6-4810-be79-f4ac295f8e7b.png",
				"subUrl": "",
				"jumpMode": 1,
				"jumpUrl": "https://www.huobi.co.ma/en-us/tradingbot/h5",
				"jumpSymbol": "",
				"weight": 109,
				"needLogin": 0,
				"androidVersion": "",
				"androidMinVersion": "",
				"iosVersion": "",
				"iosMinVersion": "",
				"description": "",
				"group": "Trade",
				"startTime": 0,
				"endTime": 0,
				"androidMaxVersion": "",
				"iosMaxVersion": "",
				"domainUrlBusiness": "主站域名",
				"countryBlackList": "",
				"newImgUrl": "https://huobi-1306115679.file.myqcloud.com/bit/appFeatures/66ce8caf-a8ce-4301-a11e-8e75a60464b8.png",
				"groupCode": "网格机器人",
				"homePageFixed": 1,
				"homePageFixedIndex": 109,
				"newModule": null,
				"sort": null
			}, {
				"id": 1014,
				"title": "Huobi NFT",
				"introduction": "",
				"imgUrl": "https://huobi-1253283450.file.myqcloud.com/bit/appFeatures/8d43564f-9814-4460-8c60-99da9c14bc7d.png",
				"imgNightUrl": "https://huobi-1253283450.file.myqcloud.com/bit/appFeatures/d87989b0-7843-4a37-8e78-6cf3915eb324.png",
				"subUrl": "",
				"jumpMode": 1,
				"jumpUrl": "https://nft.huobi.co.ma/en-us",
				"jumpSymbol": "",
				"weight": 108,
				"needLogin": 0,
				"androidVersion": "",
				"androidMinVersion": "",
				"iosVersion": "",
				"iosMinVersion": "",
				"description": "",
				"group": "Trade",
				"startTime": 0,
				"endTime": 0,
				"androidMaxVersion": "",
				"iosMaxVersion": "",
				"domainUrlBusiness": "火币NFT",
				"countryBlackList": "",
				"newImgUrl": "https://huobi-1306115679.file.myqcloud.com/bit/appFeatures/bd6c3a49-4a23-46aa-a79f-625debea5d2a.png",
				"groupCode": "火币NFT",
				"homePageFixed": 1,
				"homePageFixedIndex": 108,
				"newModule": null,
				"sort": null
			}, {
				"id": 376,
				"title": "Deposit",
				"introduction": "",
				"imgUrl": "https://huobi-1253283450.file.myqcloud.com/bit/appFeatures/3b3e121c-1137-45da-a9e3-c103155f34df.png",
				"imgNightUrl": "https://huobi-1253283450.file.myqcloud.com/bit/appFeatures/9e9885f2-0dd2-4679-93b5-c526311fb911.png",
				"subUrl": "",
				"jumpMode": 8,
				"jumpUrl": "",
				"jumpSymbol": "",
				"weight": 106,
				"needLogin": 1,
				"androidVersion": "",
				"androidMinVersion": "",
				"iosVersion": "",
				"iosMinVersion": "",
				"description": "",
				"group": "Trade",
				"startTime": 0,
				"endTime": 0,
				"androidMaxVersion": "",
				"iosMaxVersion": "",
				"domainUrlBusiness": "",
				"countryBlackList": "",
				"newImgUrl": "https://huobi-1306115679.file.myqcloud.com/bit/appFeatures/71db2a18-ed6a-4cd4-b96c-6b9e9a1774d6.png",
				"groupCode": "充币",
				"homePageFixed": 1,
				"homePageFixedIndex": 106,
				"newModule": null,
				"sort": null
			}, {
				"id": 1336,
				"title": "Options",
				"introduction": "",
				"imgUrl": "https://huobi-1306115679.file.myqcloud.com/bit/appFeatures/d3fdb76d-0a7d-435f-bb6e-0eaad98ccc5a.png",
				"imgNightUrl": "https://huobi-1306115679.file.myqcloud.com/bit/appFeatures/3737a54d-1413-4550-9640-fc2cd5314e24.png",
				"subUrl": "",
				"jumpMode": 35,
				"jumpUrl": "",
				"jumpSymbol": "",
				"weight": 95,
				"needLogin": 1,
				"androidVersion": "",
				"androidMinVersion": "",
				"iosVersion": "",
				"iosMinVersion": "",
				"description": "",
				"group": "Trade",
				"startTime": 0,
				"endTime": 0,
				"androidMaxVersion": "",
				"iosMaxVersion": "",
				"domainUrlBusiness": "",
				"countryBlackList": "",
				"newImgUrl": "https://huobi-1306115679.file.myqcloud.com/bit/appFeatures/fc66f78c-0b29-43ee-be43-744aa6b4d275.png",
				"groupCode": "期权",
				"homePageFixed": 0,
				"homePageFixedIndex": 0,
				"newModule": null,
				"sort": 26381
			}, {
				"id": 1523,
				"title": "Margin",
				"introduction": "",
				"imgUrl": "https://huobi-1306115679.file.myqcloud.com/bit/appFeatures/721e39eb-bca0-4fa0-935a-90a3328e3eb1.png",
				"imgNightUrl": "https://huobi-1306115679.file.myqcloud.com/bit/appFeatures/d255ea72-7b72-4315-9bbf-1a3e056b9b35.png",
				"subUrl": "",
				"jumpMode": 20,
				"jumpUrl": "",
				"jumpSymbol": "",
				"weight": 93,
				"needLogin": 1,
				"androidVersion": "",
				"androidMinVersion": "",
				"iosVersion": "",
				"iosMinVersion": "",
				"description": "",
				"group": "Trade",
				"startTime": 0,
				"endTime": 0,
				"androidMaxVersion": "",
				"iosMaxVersion": "",
				"domainUrlBusiness": "",
				"countryBlackList": "",
				"newImgUrl": "https://huobi-1306115679.file.myqcloud.com/bit/appFeatures/024f3d7b-511c-4a17-a4d6-eb06c4042e68.png",
				"groupCode": "杠杆",
				"homePageFixed": 0,
				"homePageFixedIndex": 0,
				"newModule": null,
				"sort": 26382
			}, {
				"id": 1213,
				"title": "Derivatives Grid Bot",
				"introduction": "",
				"imgUrl": "https://huobi-1253283450.file.myqcloud.com/bit/appFeatures/df7d0943-fd7d-41f3-adab-ae7bcab3ec48.png",
				"imgNightUrl": "https://huobi-1253283450.file.myqcloud.com/bit/appFeatures/13e80d22-6de6-4d1f-94a7-e8a7de385450.png",
				"subUrl": "",
				"jumpMode": 1,
				"jumpUrl": "https://hdm.huobi.co.ma/strategy/grid_exchange/",
				"jumpSymbol": "",
				"weight": 60,
				"needLogin": 1,
				"androidVersion": "",
				"androidMinVersion": "",
				"iosVersion": "",
				"iosMinVersion": "",
				"description": "",
				"group": "Trade",
				"startTime": 0,
				"endTime": 0,
				"androidMaxVersion": "",
				"iosMaxVersion": "",
				"domainUrlBusiness": "合约域名",
				"countryBlackList": "",
				"newImgUrl": "https://huobi-1306115679.file.myqcloud.com/bit/appFeatures/5475f1bb-dcb7-4fbd-803a-465501246142.png",
				"groupCode": "合约网格",
				"homePageFixed": 0,
				"homePageFixedIndex": 0,
				"newModule": null,
				"sort": 26389
			}]
		}, {
			"name": "Activities and Bonus",
			"list": [{
				"id": 1609,
				"title": "Newlisting",
				"introduction": "",
				"imgUrl": "https://huobi-1306115679.file.myqcloud.com/bit/appFeatures/12306542-c027-402d-808c-ef125f723110.png",
				"imgNightUrl": "https://huobi-1306115679.file.myqcloud.com/bit/appFeatures/bc850a62-761c-49a2-8555-808178c39735.png",
				"subUrl": "",
				"jumpMode": 1,
				"jumpUrl": "https://www.huobi.co.ma/en-us/topic/newlisting",
				"jumpSymbol": "",
				"weight": 99,
				"needLogin": 1,
				"androidVersion": "6.8.6|6.8.5|6.8.4|6.8.3|6.8.2|6.8.1|6.8.0|",
				"androidMinVersion": "",
				"iosVersion": "6.8.5|6.8.4|6.8.3|6.8.2|6.8.1|6.8.0|6.7.9|",
				"iosMinVersion": "",
				"description": "",
				"group": "Activities and Bonus",
				"startTime": 0,
				"endTime": 0,
				"androidMaxVersion": "",
				"iosMaxVersion": "",
				"domainUrlBusiness": "主站域名",
				"countryBlackList": "",
				"newImgUrl": "https://huobi-1306115679.file.myqcloud.com/bit/appFeatures/6c0f1a44-d5c6-4385-9f89-76322e66f0d7.gif",
				"groupCode": "Newlisting",
				"homePageFixed": 0,
				"homePageFixedIndex": 0,
				"newModule": null,
				"sort": null
			}, {
				"id": 1558,
				"title": "Rewards Hub",
				"introduction": "",
				"imgUrl": "https://huobi-1306115679.file.myqcloud.com/bit/appFeatures/203e00c0-eab8-4953-bfa7-54a897374166.png",
				"imgNightUrl": "https://huobi-1306115679.file.myqcloud.com/bit/appFeatures/0113498f-db7a-4ec1-84c3-390c787419d7.png",
				"subUrl": "",
				"jumpMode": 1,
				"jumpUrl": "https://www.huobi.co.ma/en-us/topic/welfare/h5/",
				"jumpSymbol": "",
				"weight": 98,
				"needLogin": 1,
				"androidVersion": "",
				"androidMinVersion": "",
				"iosVersion": "",
				"iosMinVersion": "",
				"description": "",
				"group": "Activities and Bonus",
				"startTime": 0,
				"endTime": 0,
				"androidMaxVersion": "",
				"iosMaxVersion": "",
				"domainUrlBusiness": "主站域名",
				"countryBlackList": "",
				"newImgUrl": "https://huobi-1306115679.file.myqcloud.com/bit/appFeatures/caed9786-f83e-46cb-afb1-c06bc0687ed7.png",
				"groupCode": "福利中心",
				"homePageFixed": 0,
				"homePageFixedIndex": 0,
				"newModule": null,
				"sort": null
			}, {
				"id": 373,
				"title": "Referral",
				"introduction": "",
				"imgUrl": "https://huobi-1306115679.file.myqcloud.com/bit/appFeatures/2bac795e-0ddf-4f15-81b1-6b2581849e75.png",
				"imgNightUrl": "https://huobi-1306115679.file.myqcloud.com/bit/appFeatures/700e9ccd-f9a3-44eb-9cea-c5dfd395e1ca.png",
				"subUrl": "",
				"jumpMode": 1,
				"jumpUrl": "https://www.huobi.co.ma/en-us/double-invite-retail/h5",
				"jumpSymbol": "",
				"weight": 96,
				"needLogin": 0,
				"androidVersion": "6.8.6|6.8.5|6.8.4|6.8.3|6.8.2|6.8.1|6.8.0|",
				"androidMinVersion": "",
				"iosVersion": "6.8.5|6.8.4|6.8.3|6.8.2|6.8.1|6.8.0|6.7.9|",
				"iosMinVersion": "",
				"description": "",
				"group": "Activities and Bonus",
				"startTime": 0,
				"endTime": 0,
				"androidMaxVersion": "",
				"iosMaxVersion": "",
				"domainUrlBusiness": "主站域名",
				"countryBlackList": "",
				"newImgUrl": "https://huobi-1306115679.file.myqcloud.com/bit/appFeatures/58697a69-a748-4af1-8baa-e0f7c5efbdfa.gif",
				"groupCode": "邀请返佣",
				"homePageFixed": 0,
				"homePageFixedIndex": 0,
				"newModule": null,
				"sort": null
			}, {
				"id": 1444,
				"title": "Trade Spin",
				"introduction": "",
				"imgUrl": "https://huobi-1306115679.file.myqcloud.com/bit/appFeatures/c86d4cdc-4f6f-4de3-bbb2-ea98d4cd92f5.png",
				"imgNightUrl": "https://huobi-1306115679.file.myqcloud.com/bit/appFeatures/0b203bbe-27dd-4116-a4de-33e4cb581cf7.png",
				"subUrl": "",
				"jumpMode": 1,
				"jumpUrl": "https://www.huobi.co.ma/en-us/topic/trading-activity-tmpl/h5/?code=Lottery220512124654",
				"jumpSymbol": "",
				"weight": 92,
				"needLogin": 1,
				"androidVersion": "6.5.9|6.5.8|6.5.7|6.5.4|",
				"androidMinVersion": "",
				"iosVersion": "6.5.9|6.5.8|6.5.7|6.5.3|6.5.2|",
				"iosMinVersion": "",
				"description": "",
				"group": "Activities and Bonus",
				"startTime": 0,
				"endTime": 0,
				"androidMaxVersion": "",
				"iosMaxVersion": "",
				"domainUrlBusiness": "主站域名",
				"countryBlackList": "",
				"newImgUrl": "https://huobi-1306115679.file.myqcloud.com/bit/appFeatures/dc479aa5-2d67-4b3c-8064-2255eb2b23ac.png",
				"groupCode": "引力",
				"homePageFixed": 0,
				"homePageFixedIndex": 0,
				"newModule": null,
				"sort": 26383
			}, {
				"id": 510,
				"title": "Derivatives Coupon",
				"introduction": "",
				"imgUrl": "https://huobi-1253283450.file.myqcloud.com/bit/appFeatures/1e681c07-6a53-4207-8621-70cfdd582ccb.png",
				"imgNightUrl": "https://huobi-1253283450.file.myqcloud.com/bit/appFeatures/b2f913b0-d3b4-48a8-9919-72548b52ceaf.png",
				"subUrl": "",
				"jumpMode": 1,
				"jumpUrl": "https://hdm.huobi.co.ma/coupon",
				"jumpSymbol": "",
				"weight": 48,
				"needLogin": 1,
				"androidVersion": "6.4.4|6.4.3|6.4.2|6.4.1|6.4.0|6.3.9|6.3.8|",
				"androidMinVersion": "",
				"iosVersion": "6.4.4|6.4.3|6.4.2|6.4.1|6.4.0|6.3.9|6.3.8|",
				"iosMinVersion": "",
				"description": "",
				"group": "Activities and Bonus",
				"startTime": 0,
				"endTime": 0,
				"androidMaxVersion": "",
				"iosMaxVersion": "",
				"domainUrlBusiness": "合约域名",
				"countryBlackList": "",
				"newImgUrl": "https://huobi-1306115679.file.myqcloud.com/bit/appFeatures/3362a447-8a75-4a28-9531-4bbda4a5d677.png",
				"groupCode": "合约手续费抵扣券",
				"homePageFixed": 0,
				"homePageFixedIndex": 0,
				"newModule": null,
				"sort": null
			}]
		}, {
			"name": "Finance",
			"list": [{
				"id": 1351,
				"title": "Dual Investment",
				"introduction": "",
				"imgUrl": "https://huobi-1306115679.file.myqcloud.com/bit/appFeatures/b295bb58-6456-4ba0-8485-74050bdb863f.png",
				"imgNightUrl": "https://huobi-1306115679.file.myqcloud.com/bit/appFeatures/116604cc-3fa4-47f6-b0e7-16c9227534e8.png",
				"subUrl": "",
				"jumpMode": 1,
				"jumpUrl": "https://www.huobi.co.ma/en-us/otc-option/win/h5",
				"jumpSymbol": "",
				"weight": 107,
				"needLogin": 0,
				"androidVersion": "",
				"androidMinVersion": "",
				"iosVersion": "",
				"iosMinVersion": "",
				"description": "",
				"group": "Finance",
				"startTime": 0,
				"endTime": 0,
				"androidMaxVersion": "",
				"iosMaxVersion": "",
				"domainUrlBusiness": "主站域名",
				"countryBlackList": "",
				"newImgUrl": "https://huobi-1306115679.file.myqcloud.com/bit/appFeatures/7c41a570-8aa9-4e73-a5f3-8878efe53514.png",
				"groupCode": "双币投资",
				"homePageFixed": 1,
				"homePageFixedIndex": 107,
				"newModule": null,
				"sort": null
			}, {
				"id": 381,
				"title": "Earn",
				"introduction": "",
				"imgUrl": "https://huobi-1253283450.file.myqcloud.com/bit/appFeatures/06fee7d0-c0b5-41ea-91da-8713481655e9.png",
				"imgNightUrl": "https://huobi-1253283450.file.myqcloud.com/bit/appFeatures/aa3ee4c6-fb41-4968-b813-d2612f25160f.png",
				"subUrl": "",
				"jumpMode": 1,
				"jumpUrl": "https://www.huobi.co.ma/en-us/financial/earnings/h5",
				"jumpSymbol": "",
				"weight": 97,
				"needLogin": 1,
				"androidVersion": "",
				"androidMinVersion": "",
				"iosVersion": "",
				"iosMinVersion": "",
				"description": "",
				"group": "Finance",
				"startTime": 0,
				"endTime": 0,
				"androidMaxVersion": "",
				"iosMaxVersion": "",
				"domainUrlBusiness": "主站域名",
				"countryBlackList": "",
				"newImgUrl": "https://huobi-1306115679.file.myqcloud.com/bit/appFeatures/72fb9eac-1740-4938-933f-dee9d04bda37.png",
				"groupCode": "Huobi Earn",
				"homePageFixed": 0,
				"homePageFixedIndex": 0,
				"newModule": null,
				"sort": 26380
			}, {
				"id": 382,
				"title": "ETH 2.0",
				"introduction": "",
				"imgUrl": "https://huobi-1253283450.file.myqcloud.com/bit/appFeatures/3585291e-9f34-4380-b3d9-59be766de553.png",
				"imgNightUrl": "https://huobi-1253283450.file.myqcloud.com/bit/appFeatures/efe7652e-d37a-43d9-af64-22e67c0b83da.png",
				"subUrl": "",
				"jumpMode": 1,
				"jumpUrl": "https://pool.huobi.co.ma/pool/en-us/topic/eth/h5?refresh=2&color=060C30&hideNav=1",
				"jumpSymbol": "",
				"weight": 88,
				"needLogin": 0,
				"androidVersion": "",
				"androidMinVersion": "",
				"iosVersion": "",
				"iosMinVersion": "",
				"description": "",
				"group": "Finance",
				"startTime": 0,
				"endTime": 0,
				"androidMaxVersion": "",
				"iosMaxVersion": "",
				"domainUrlBusiness": "",
				"countryBlackList": "",
				"newImgUrl": "https://huobi-1306115679.file.myqcloud.com/bit/appFeatures/50b5bea9-4c8b-472c-9c27-787574afdb0b.png",
				"groupCode": "以太坊2.0",
				"homePageFixed": 0,
				"homePageFixedIndex": 0,
				"newModule": null,
				"sort": 26386
			}, {
				"id": 682,
				"title": "Crypto Loans",
				"introduction": "",
				"imgUrl": "https://huobi-1253283450.file.myqcloud.com/bit/appFeatures/f5642537-a7b5-47c9-9036-e18fa293d44f.png",
				"imgNightUrl": "https://huobi-1253283450.file.myqcloud.com/bit/appFeatures/9bba46a7-3ffc-4cf2-af95-435885c47c27.png",
				"subUrl": "",
				"jumpMode": 1,
				"jumpUrl": "https://pledge.huobi.co.ma/pledge/?hideNav=1",
				"jumpSymbol": "",
				"weight": 87,
				"needLogin": 1,
				"androidVersion": "6.4.4|6.4.3|6.4.2|6.4.1|6.4.0|6.3.9|6.3.8|",
				"androidMinVersion": "",
				"iosVersion": "6.4.4|6.4.3|6.4.2|6.4.1|6.4.0|6.3.9|6.3.8|",
				"iosMinVersion": "",
				"description": "",
				"group": "Finance",
				"startTime": 0,
				"endTime": 0,
				"androidMaxVersion": "",
				"iosMaxVersion": "",
				"domainUrlBusiness": "质押借贷",
				"countryBlackList": "",
				"newImgUrl": "https://huobi-1306115679.file.myqcloud.com/bit/appFeatures/f11e8780-6e60-4022-b823-0bd48474afa4.png",
				"groupCode": "质押借币",
				"homePageFixed": 0,
				"homePageFixedIndex": 0,
				"newModule": null,
				"sort": 26387
			}, {
				"id": 475,
				"title": "Staking",
				"introduction": "",
				"imgUrl": "https://huobi-1253283450.file.myqcloud.com/bit/appFeatures/4ebc1f9e-8317-4f63-98a8-e3772ee092c2.png",
				"imgNightUrl": "https://huobi-1253283450.file.myqcloud.com/bit/appFeatures/1cc6d0ba-93da-445a-b801-7b038a0733d5.png",
				"subUrl": "",
				"jumpMode": 1,
				"jumpUrl": "https://www.huobi.co.ma/en-us/staking/vote/h5",
				"jumpSymbol": "",
				"weight": 86,
				"needLogin": 0,
				"androidVersion": "6.3.2|6.3.1|",
				"androidMinVersion": "",
				"iosVersion": "6.3.2|6.3.1|",
				"iosMinVersion": "",
				"description": "",
				"group": "Finance",
				"startTime": 0,
				"endTime": 0,
				"androidMaxVersion": "",
				"iosMaxVersion": "",
				"domainUrlBusiness": "主站域名",
				"countryBlackList": "",
				"newImgUrl": "https://huobi-1306115679.file.myqcloud.com/bit/appFeatures/848df22c-4fb2-45e0-85d8-9c73446ae58c.png",
				"groupCode": "节点投票",
				"homePageFixed": 0,
				"homePageFixedIndex": 0,
				"newModule": null,
				"sort": 26388
			}, {
				"id": 882,
				"title": "PolkaDOT Auction",
				"introduction": "",
				"imgUrl": "https://huobi-1253283450.file.myqcloud.com/bit/appFeatures/f9228fc3-4f5d-41f3-9aad-fdf3169c83da.png",
				"imgNightUrl": "https://huobi-1253283450.file.myqcloud.com/bit/appFeatures/f33292f5-0595-48f9-9bca-9c66a59805f8.png",
				"subUrl": "",
				"jumpMode": 1,
				"jumpUrl": "https://www.huobi.co.ma/en-us/topic/dot-slot/h5/",
				"jumpSymbol": "",
				"weight": 40,
				"needLogin": 0,
				"androidVersion": "6.3.6|6.3.5|6.3.4|6.3.3|6.3.2|6.3.1|6.3.0|6.2.9|6.2.8|6.2.7|6.2.6|6.2.5|6.2.4|6.2.3|6.2.2|6.2.1|6.2.0|6.1.9|",
				"androidMinVersion": "",
				"iosVersion": "6.3.6|6.3.5|6.3.4|6.3.3|6.3.2|6.3.1|6.3.0|6.2.9|6.2.8|6.2.7|6.2.6|6.2.5|6.2.4|6.2.3|6.2.2|6.2.1|6.2.0|6.1.9|",
				"iosMinVersion": "",
				"description": "",
				"group": "Finance",
				"startTime": 0,
				"endTime": 0,
				"androidMaxVersion": "",
				"iosMaxVersion": "",
				"domainUrlBusiness": "主站域名",
				"countryBlackList": "",
				"newImgUrl": "https://huobi-1306115679.file.myqcloud.com/bit/appFeatures/13e84476-4674-437e-b286-be9ec9471546.png",
				"groupCode": "波卡卡槽竞拍",
				"homePageFixed": 0,
				"homePageFixedIndex": 0,
				"newModule": null,
				"sort": null
			}]
		}, {
			"name": "Ecosystem",
			"list": [{
				"id": 387,
				"title": "ETH ECO",
				"introduction": "",
				"imgUrl": "https://huobi-1253283450.file.myqcloud.com/bit/appFeatures/393efa17-4c2b-45ef-828a-a965bae48d74.png",
				"imgNightUrl": "https://huobi-1253283450.file.myqcloud.com/bit/appFeatures/fa133548-d530-4866-82ff-b415debacfb9.png",
				"subUrl": "",
				"jumpMode": 1,
				"jumpUrl": "https://www.huobi.co.ma/en-us/topic/defi/h5/?hideNav=1&r=20200819",
				"jumpSymbol": "",
				"weight": 30,
				"needLogin": 0,
				"androidVersion": "",
				"androidMinVersion": "",
				"iosVersion": "",
				"iosMinVersion": "",
				"description": "",
				"group": "Ecosystem",
				"startTime": 0,
				"endTime": 0,
				"androidMaxVersion": "",
				"iosMaxVersion": "",
				"domainUrlBusiness": "主站域名",
				"countryBlackList": "",
				"newImgUrl": "https://huobi-1306115679.file.myqcloud.com/bit/appFeatures/b810c52e-fdbf-4824-8b79-f68d21a53450.png",
				"groupCode": "以太坊生态",
				"homePageFixed": 0,
				"homePageFixedIndex": 0,
				"newModule": null,
				"sort": null
			}, {
				"id": 388,
				"title": "Storage Zone",
				"introduction": "",
				"imgUrl": "https://huobi-1253283450.file.myqcloud.com/bit/appFeatures/5ed3ec83-5538-4c20-9cc0-0062e8521948.png",
				"imgNightUrl": "https://huobi-1253283450.file.myqcloud.com/bit/appFeatures/7e8739f5-8e79-4371-b6be-af62c4311f16.png",
				"subUrl": "",
				"jumpMode": 1,
				"jumpUrl": "https://www.huobi.co.ma/en-us/topic/storage/h5/?hideNav=1",
				"jumpSymbol": "",
				"weight": 29,
				"needLogin": 0,
				"androidVersion": "",
				"androidMinVersion": "",
				"iosVersion": "",
				"iosMinVersion": "",
				"description": "",
				"group": "Ecosystem",
				"startTime": 0,
				"endTime": 0,
				"androidMaxVersion": "",
				"iosMaxVersion": "",
				"domainUrlBusiness": "主站域名",
				"countryBlackList": "",
				"newImgUrl": "https://huobi-1306115679.file.myqcloud.com/bit/appFeatures/130a857f-30f5-43f8-9958-8dbba23f3ce2.png",
				"groupCode": "存储板块",
				"homePageFixed": 0,
				"homePageFixedIndex": 0,
				"newModule": null,
				"sort": null
			}, {
				"id": 383,
				"title": "Polkadot ECO",
				"introduction": "",
				"imgUrl": "https://huobi-1253283450.file.myqcloud.com/bit/appFeatures/304bc37d-4ea0-44d8-9fb2-dd54ab395f83.png",
				"imgNightUrl": "https://huobi-1253283450.file.myqcloud.com/bit/appFeatures/a7286045-95a5-49bf-8b70-e4e7c1bdb126.png",
				"subUrl": "",
				"jumpMode": 1,
				"jumpUrl": "https://www.huobi.co.ma/en-us/topic/dot/h5/",
				"jumpSymbol": "",
				"weight": 28,
				"needLogin": 0,
				"androidVersion": "6.3.2|6.3.1|",
				"androidMinVersion": "",
				"iosVersion": "6.3.2|6.3.1|",
				"iosMinVersion": "",
				"description": "",
				"group": "Ecosystem",
				"startTime": 0,
				"endTime": 0,
				"androidMaxVersion": "",
				"iosMaxVersion": "",
				"domainUrlBusiness": "主站域名",
				"countryBlackList": "",
				"newImgUrl": "https://huobi-1306115679.file.myqcloud.com/bit/appFeatures/01045a8e-2572-4960-a682-be7dc12bd157.png",
				"groupCode": "波卡生态板块",
				"homePageFixed": 0,
				"homePageFixedIndex": 0,
				"newModule": null,
				"sort": null
			}]
		}, {
			"name": "Information",
			"list": [{
				"id": 1483,
				"title": "Huobi Live",
				"introduction": "",
				"imgUrl": "https://huobi-1306115679.file.myqcloud.com/bit/appFeatures/b1657ef1-331c-428f-9f8a-8b4056144e4c.gif",
				"imgNightUrl": "https://huobi-1306115679.file.myqcloud.com/bit/appFeatures/d6c3a826-65b2-4ecd-abd6-272d4e596041.gif",
				"subUrl": "",
				"jumpMode": 40,
				"jumpUrl": "",
				"jumpSymbol": "",
				"weight": 100,
				"needLogin": 0,
				"androidVersion": "6.8.6|6.8.5|6.8.4|6.8.3|6.8.2|6.8.1|6.8.0|",
				"androidMinVersion": "",
				"iosVersion": "6.8.5|6.8.4|6.8.3|6.8.2|6.8.1|6.8.0|6.7.9|",
				"iosMinVersion": "",
				"description": "",
				"group": "Information",
				"startTime": 1648440000000,
				"endTime": 0,
				"androidMaxVersion": "",
				"iosMaxVersion": "",
				"domainUrlBusiness": "",
				"countryBlackList": "",
				"newImgUrl": "https://huobi-1306115679.file.myqcloud.com/bit/appFeatures/371697f9-d231-4433-89d9-e179b3911ccf.png",
				"groupCode": "直播",
				"homePageFixed": 0,
				"homePageFixedIndex": 0,
				"newModule": null,
				"sort": null
			}, {
				"id": 1013,
				"title": "Huobi Learn",
				"introduction": "",
				"imgUrl": "https://huobi-1253283450.file.myqcloud.com/bit/appFeatures/719840a4-91ca-4b49-b171-094319ef5886.png",
				"imgNightUrl": "https://huobi-1253283450.file.myqcloud.com/bit/appFeatures/de39037d-44e0-4586-b43a-a84e98377998.png",
				"subUrl": "",
				"jumpMode": 1,
				"jumpUrl": "https://www.huobi.co.ma/learn/en-us/",
				"jumpSymbol": "",
				"weight": 90,
				"needLogin": 0,
				"androidVersion": "",
				"androidMinVersion": "",
				"iosVersion": "",
				"iosMinVersion": "",
				"description": "",
				"group": "Information",
				"startTime": 0,
				"endTime": 0,
				"androidMaxVersion": "",
				"iosMaxVersion": "",
				"domainUrlBusiness": "主站域名",
				"countryBlackList": "",
				"newImgUrl": "https://huobi-1306115679.file.myqcloud.com/bit/appFeatures/c128e6db-b24a-4921-8eec-32d512013100.png",
				"groupCode": "成长学院",
				"homePageFixed": 0,
				"homePageFixedIndex": 0,
				"newModule": null,
				"sort": 26385
			}]
		}, {
			"name": "Service",
			"list": [{
				"id": 377,
				"title": "Chat",
				"introduction": "",
				"imgUrl": "https://huobi-1253283450.file.myqcloud.com/bit/appFeatures/cf934879-fad2-41e9-86f0-c5a2fc54090a.png",
				"imgNightUrl": "https://huobi-1253283450.file.myqcloud.com/bit/appFeatures/37a770ce-b00c-4675-99bf-1738415b04d9.png",
				"subUrl": "",
				"jumpMode": 7,
				"jumpUrl": "",
				"jumpSymbol": "",
				"weight": 91,
				"needLogin": 0,
				"androidVersion": "",
				"androidMinVersion": "",
				"iosVersion": "",
				"iosMinVersion": "",
				"description": "",
				"group": "Service",
				"startTime": 0,
				"endTime": 0,
				"androidMaxVersion": "",
				"iosMaxVersion": "",
				"domainUrlBusiness": "",
				"countryBlackList": "",
				"newImgUrl": "https://huobi-1306115679.file.myqcloud.com/bit/appFeatures/8e48e298-7460-4b1d-abcf-088fee084083.png",
				"groupCode": "客服",
				"homePageFixed": 0,
				"homePageFixedIndex": 0,
				"newModule": null,
				"sort": 26384
			}]
		}]
	}
}
